runorangerun/__init__.py
runorangerun/runorangerun.py
runorangerun-1.0.0.data/data/1.PNG
runorangerun-1.0.0.data/data/10.PNG
runorangerun-1.0.0.data/data/11.PNG
runorangerun-1.0.0.data/data/12.PNG
runorangerun-1.0.0.data/data/13.PNG
runorangerun-1.0.0.data/data/14.PNG
runorangerun-1.0.0.data/data/15.PNG
runorangerun-1.0.0.data/data/16.PNG
runorangerun-1.0.0.data/data/17.PNG
runorangerun-1.0.0.data/data/2.PNG
runorangerun-1.0.0.data/data/3.PNG
runorangerun-1.0.0.data/data/4.PNG
runorangerun-1.0.0.data/data/5.PNG
runorangerun-1.0.0.data/data/6.PNG
runorangerun-1.0.0.data/data/7.PNG
runorangerun-1.0.0.data/data/8.PNG
runorangerun-1.0.0.data/data/9.PNG
runorangerun-1.0.0.data/data/Surreal-Chase_Looping.mp3
runorangerun-1.0.0.data/data/blend2.png
runorangerun-1.0.0.data/data/button.ogg
runorangerun-1.0.0.data/data/gameOverMenu.png
runorangerun-1.0.0.data/data/instruction.png
runorangerun-1.0.0.data/data/juicer.png
runorangerun-1.0.0.data/data/juicer2.png
runorangerun-1.0.0.data/data/jump_11.wav
runorangerun-1.0.0.data/data/knife.png
runorangerun-1.0.0.data/data/knifeRack.png
runorangerun-1.0.0.data/data/mainPage.png
runorangerun-1.0.0.data/data/orangeJumping.png
runorangerun-1.0.0.data/data/pause menu.png
runorangerun-1.0.0.data/data/rolling1.png
runorangerun-1.0.0.data/data/rolling2.png
runorangerun-1.0.0.data/data/sound menu.png
runorangerun-1.0.0.data/data/wallpaper.png
runorangerun-1.0.0.data/data/wallpaper2.png
runorangerun-1.0.0.data/data/whoosh.wav
runorangerun-1.0.0.data/scripts/runorangerun
runorangerun-1.0.0.dist-info/METADATA
runorangerun-1.0.0.dist-info/WHEEL
runorangerun-1.0.0.dist-info/top_level.txt
runorangerun-1.0.0.dist-info/RECORD
