Metadata-Version: 2.1
Name: runorangerun
Version: 1.0.0
Summary: shari shari shari
Home-page: https://github.com/shari09/gr10-game-Run-Orange-Run
Author: Shari
Author-email: shari09cxxcr@gmail.com
License: UNKNOWN
Keywords: shari chari cherry
Platform: UNKNOWN
Requires-Python: >=3.6
Requires-Dist: pygame
